txapi/__init__.py
txapi/api2.py
txapi/api3.py
txapi/version.py
txapi/QcloudApi/__init__.py
txapi/QcloudApi/qcloudapi.py
txapi/QcloudApi/common/__init__.py
txapi/QcloudApi/common/api_exception.py
txapi/QcloudApi/common/request.py
txapi/QcloudApi/common/sign.py
txapi/QcloudApi/modules/__init__.py
txapi/QcloudApi/modules/base.py
txapi/demo/__init__.py
txapi/demo/config.py
txapi/demo/demo.py
txapi/tencentcloud/__init__.py
txapi/tencentcloud/common/__init__.py
txapi/tencentcloud/common/abstract_client.py
txapi/tencentcloud/common/abstract_model.py
txapi/tencentcloud/common/credential.py
txapi/tencentcloud/common/sign.py
txapi/tencentcloud/common/exception/__init__.py
txapi/tencentcloud/common/exception/tencent_cloud_sdk_exception.py
txapi/tencentcloud/common/http/__init__.py
txapi/tencentcloud/common/http/request.py
txapi/tencentcloud/common/profile/__init__.py
txapi/tencentcloud/common/profile/client_profile.py
txapi/tencentcloud/common/profile/http_profile.py
txapi-1.0.0.dist-info/METADATA
txapi-1.0.0.dist-info/WHEEL
txapi-1.0.0.dist-info/top_level.txt
txapi-1.0.0.dist-info/RECORD
