Metadata-Version: 2.1
Name: txapi
Version: 1.0.0
Summary: api project for v2&v3
Home-page: https://github.com/coreylam/txapi
Author: coreylam
Author-email: coreylam@163.com
